[{"id":1,"nameRoom":"São Borja Airport","descripton":"Removal of Extraluminal Device from Left Eye, Open Approach","price":"$763.31","priceDiscount":"$226.90"},
{"id":2,"nameRoom":"Vilankulo Airport","descripton":"Excision of Peroneal Nerve, Percutaneous Approach, Diagn","price":"$177.10","priceDiscount":"$747.16"},
{"id":3,"nameRoom":"Fleetlands Heliport","descripton":"Bypass Innom Art to Bi Up Leg Art w Autol Vn, Open","price":"$196.12","priceDiscount":"$318.41"},
{"id":4,"nameRoom":"Quảng Ngãi Airfield","descripton":"Beam Radiation of Hard Palate using Photons 1 - 10 MeV","price":"$621.09","priceDiscount":"$288.61"},
{"id":5,"nameRoom":"Gabbs Airport","descripton":"Removal of Brace on Left Upper Arm","price":"$312.38","priceDiscount":"$728.48"},
{"id":6,"nameRoom":"Maun Airport","descripton":"Release Left Lesser Saphenous Vein, Open Approach","price":"$145.78","priceDiscount":"$821.62"},
{"id":7,"nameRoom":"Konge Airport","descripton":"Drainage of Left Carpal Joint, Percutaneous Approach, Diagn","price":"$424.73","priceDiscount":"$721.40"},
{"id":8,"nameRoom":"Igiugig Airport","descripton":"Removal of Autol Sub from L Acromioclav Jt, Perc Approach","price":"$244.71","priceDiscount":"$216.46"},
{"id":9,"nameRoom":"Innisfail Airport","descripton":"Extirpate matter from Conduction Mechanism, Perc Endo","price":"$188.08","priceDiscount":"$138.61"},
{"id":10,"nameRoom":"Matão Airport","descripton":"Supplement Hyoid Bone with Nonaut Sub, Perc Approach","price":"$812.71","priceDiscount":"$706.26"},
{"id":11,"nameRoom":"Malamala Airport","descripton":"Dilate L Fem Art, Bifurc, w 3 Drug-elut, Perc Endo","price":"$179.50","priceDiscount":"$657.05"},
{"id":12,"nameRoom":"Fulleborn Airport","descripton":"Fluoroscopy of Right Renal Artery using Low Osmolar Contrast","price":"$268.82","priceDiscount":"$704.25"},
{"id":13,"nameRoom":"Bintulu Airport","descripton":"Repair Spleen, Percutaneous Endoscopic Approach","price":"$959.70","priceDiscount":"$833.10"},
{"id":14,"nameRoom":"Dr. Antonio Nicolás Briceño Airport","descripton":"Bypass L Hepatic Duct to Caud Duct w Intralum Dev, Open","price":"$577.35","priceDiscount":"$689.12"},
{"id":15,"nameRoom":"Efogi Airport","descripton":"Fusion of L Finger Phalanx Jt with Autol Sub, Open Approach","price":"$799.72","priceDiscount":"$629.53"},
{"id":16,"nameRoom":"Thylungra Airport","descripton":"Drainage of Right Trunk Bursa and Ligament, Perc Approach","price":"$432.58","priceDiscount":"$730.85"},
{"id":17,"nameRoom":"Glenormiston Airport","descripton":"Supplement Lower Lip with Nonaut Sub, Perc Approach","price":"$984.09","priceDiscount":"$815.25"},
{"id":18,"nameRoom":"Kuqa Airport","descripton":"Dilation of L Ulnar Art with Drug-elut Intra, Open Approach","price":"$432.69","priceDiscount":"$247.82"},
{"id":19,"nameRoom":"Carlisle Airport","descripton":"Drainage of Right Kidney, Via Natural or Artificial Opening","price":"$607.83","priceDiscount":"$839.97"},
{"id":20,"nameRoom":"Agartala Airport","descripton":"Extirpation of Matter from Right Hand Vein, Open Approach","price":"$209.41","priceDiscount":"$211.34"}]